circle/__init__.py
circle/web3/__init__.py
circle/web3/smart_contract_platform/__init__.py
circle/web3/smart_contract_platform/api_client.py
circle/web3/smart_contract_platform/api_response.py
circle/web3/smart_contract_platform/configuration.py
circle/web3/smart_contract_platform/exceptions.py
circle/web3/smart_contract_platform/py.typed
circle/web3/smart_contract_platform/rest.py
circle/web3/smart_contract_platform/api/__init__.py
circle/web3/smart_contract_platform/api/deploy_import_api.py
circle/web3/smart_contract_platform/api/event_monitors_api.py
circle/web3/smart_contract_platform/api/interact_api.py
circle/web3/smart_contract_platform/api/templates_api.py
circle/web3/smart_contract_platform/api/view_update_api.py
circle/web3/smart_contract_platform/models/__init__.py
circle/web3/smart_contract_platform/models/abi_parameters_inner.py
circle/web3/smart_contract_platform/models/blockchain.py
circle/web3/smart_contract_platform/models/contract.py
circle/web3/smart_contract_platform/models/contract_deployment.py
circle/web3/smart_contract_platform/models/contract_deployment_data.py
circle/web3/smart_contract_platform/models/contract_deployment_estimate_fee_request.py
circle/web3/smart_contract_platform/models/contract_deployment_estimate_request.py
circle/web3/smart_contract_platform/models/contract_deployment_request.py
circle/web3/smart_contract_platform/models/contract_input_type.py
circle/web3/smart_contract_platform/models/contract_response.py
circle/web3/smart_contract_platform/models/contract_response_data.py
circle/web3/smart_contract_platform/models/contract_status.py
circle/web3/smart_contract_platform/models/contracts.py
circle/web3/smart_contract_platform/models/contracts_data.py
circle/web3/smart_contract_platform/models/create_event_monitor_request.py
circle/web3/smart_contract_platform/models/error.py
circle/web3/smart_contract_platform/models/event.py
circle/web3/smart_contract_platform/models/event_log.py
circle_smart_contract_platform-9.1.0.dist-info/METADATA
circle_smart_contract_platform-9.1.0.dist-info/WHEEL
circle_smart_contract_platform-9.1.0.dist-info/top_level.txt
circle_smart_contract_platform-9.1.0.dist-info/RECORD
