Metadata-Version: 2.4
Name: circle-smart-contract-platform
Version: 9.1.0
Summary: Circle Contracts
Home-page: 
Author: OpenAPI Generator community
Author-email: team@openapitools.org
Keywords: OpenAPI,OpenAPI-Generator,Circle Contracts
Requires-Dist: urllib3<3.0.0,>=2.1.0
Requires-Dist: python-dateutil>=2.8.2
Requires-Dist: pydantic>=2
Requires-Dist: typing-extensions>=4.7.1
Requires-Dist: lazy-imports<2,>=1
Requires-Dist: pycryptodome>=3.20.0
Requires-Dist: circle-configurations==9.1.0
Requires-Dist: circle-web3-sdk-util==9.1.0
Dynamic: author
Dynamic: author-email
Dynamic: description
Dynamic: description-content-type
Dynamic: keywords
Dynamic: requires-dist
Dynamic: summary
